{
  "roleName": "Service Group Contributor",
  "type": "BuiltInRole",
  "description": "Role Definition for contributor of a Service Group",
  "assignableScopes": [
    "/providers/Microsoft.Management/serviceGroups"
  ],
  "permissions": [
    {
      "actions": [
        "*"
      ],
      "notActions": [
        "Microsoft.Authorization/roleAssignments/write",
        "Microsoft.Authorization/roleAssignments/delete"
      ],
      "dataActions": [],
      "notDataActions": []
    }
  ],
  "createdOn": "2024-10-18T18:43:56.1898722Z",
  "updatedOn": "2024-10-18T18:43:56.1898722Z",
  "createdBy": null,
  "updatedBy": null
}
